odoo/addons/pos_margin_accounting_role/README.rst
odoo/addons/pos_margin_accounting_role/__init__.py
odoo/addons/pos_margin_accounting_role/__manifest__.py
odoo/addons/pos_margin_accounting_role/i18n/it.po
odoo/addons/pos_margin_accounting_role/i18n/pos_margin_accounting_role.pot
odoo/addons/pos_margin_accounting_role/readme/CONTRIBUTORS.rst
odoo/addons/pos_margin_accounting_role/readme/DESCRIPTION.rst
odoo/addons/pos_margin_accounting_role/static/description/icon.png
odoo/addons/pos_margin_accounting_role/static/description/index.html
odoo/addons/pos_margin_accounting_role/views/view_pos_order.xml
odoo12_addon_pos_margin_accounting_role-12.0.1.0.0.99.dev4.dist-info/METADATA
odoo12_addon_pos_margin_accounting_role-12.0.1.0.0.99.dev4.dist-info/WHEEL
odoo12_addon_pos_margin_accounting_role-12.0.1.0.0.99.dev4.dist-info/top_level.txt
odoo12_addon_pos_margin_accounting_role-12.0.1.0.0.99.dev4.dist-info/RECORD
